_cyth.cp310-win_amd64.pyd
ezeriah/__init__.py
ezeriah/_cyth.cp310-win_amd64.pyd
ezeriah/cyth.py
ezeriah/init.py
ezeriah-0.0.10.dist-info/METADATA
ezeriah-0.0.10.dist-info/WHEEL
ezeriah-0.0.10.dist-info/top_level.txt
ezeriah-0.0.10.dist-info/RECORD
